yt_concat/__init__.py
yt_concat/main.py
yt_concat/settings.py
yt_concat/utils.py
yt_concat/model/__init__.py
yt_concat/model/found.py
yt_concat/model/yt.py
yt_concat/pipeline/__init__.py
yt_concat/pipeline/pipeline.py
yt_concat/pipeline/steps/__init__.py
yt_concat/pipeline/steps/cleanup.py
yt_concat/pipeline/steps/download_captions.py
yt_concat/pipeline/steps/download_videos.py
yt_concat/pipeline/steps/edit_video.py
yt_concat/pipeline/steps/get_video_list.py
yt_concat/pipeline/steps/helpers.py
yt_concat/pipeline/steps/initialize_yt.py
yt_concat/pipeline/steps/postflight.py
yt_concat/pipeline/steps/preflight.py
yt_concat/pipeline/steps/read_caption.py
yt_concat/pipeline/steps/search.py
yt_concat/pipeline/steps/step.py
yt_concate/__init__.py
yt_concate/main.py
yt_concate/settings.py
yt_concate/utils.py
yt_concate/pipeline/__init__.py
yt_concate/pipeline/pipeline.py
yt_concate/pipeline/steps/__init__.py
yt_concate/pipeline/steps/cleanup.py
yt_concate/pipeline/steps/download_captions.py
yt_concate/pipeline/steps/download_videos.py
yt_concate/pipeline/steps/edit_video.py
yt_concate/pipeline/steps/get_video_list.py
yt_concate/pipeline/steps/helpers.py
yt_concate/pipeline/steps/initialize_yt.py
yt_concate/pipeline/steps/postflight.py
yt_concate/pipeline/steps/preflight.py
yt_concate/pipeline/steps/read_caption.py
yt_concate/pipeline/steps/search.py
yt_concate/pipeline/steps/step.py
yt_concat-0.1.7.dist-info/LICENSE
yt_concat-0.1.7.dist-info/METADATA
yt_concat-0.1.7.dist-info/WHEEL
yt_concat-0.1.7.dist-info/top_level.txt
yt_concat-0.1.7.dist-info/RECORD
