Metadata-Version: 2.2
Name: yt-concat
Version: 0.1.7
Summary: Produce a concatenated video of clips that mention a specific word from the YouTube channel.
Home-page: https://github.com/Eugene526/yt-concate/tree/main
Author: Eugene Chan
Author-email: null4047699@gmail.com
License: MIT
Classifier: License :: OSI Approved :: MIT License
Classifier: Programming Language :: Python
Classifier: Programming Language :: Python :: 3
Classifier: Programming Language :: Python :: 3.6
Classifier: Programming Language :: Python :: Implementation :: CPython
Classifier: Programming Language :: Python :: Implementation :: PyPy
Requires-Python: >=3.12.0
License-File: LICENSE
Requires-Dist: requests
Requires-Dist: moviepy
Requires-Dist: numpy
Requires-Dist: Pillow
Requires-Dist: python-dotenv
Requires-Dist: pytube
Requires-Dist: tqdm
Requires-Dist: webvtt-py
Requires-Dist: yt-dlp
Dynamic: author
Dynamic: author-email
Dynamic: classifier
Dynamic: description
Dynamic: description-content-type
Dynamic: home-page
Dynamic: license
Dynamic: requires-dist
Dynamic: requires-python
Dynamic: summary
